anntonia_keras/__init__.py
anntonia_keras/keras_reader.py
anntonia_keras-0.0.2.dist-info/METADATA
anntonia_keras-0.0.2.dist-info/WHEEL
anntonia_keras-0.0.2.dist-info/licenses/LICENSE
anntonia_keras-0.0.2.dist-info/RECORD
