Metadata-Version: 2.1
Name: anntonia_keras
Version: 0.0.2
Summary: An extension for the anntonia package to support reading keras models
Project-URL: Homepage, https://vr.rwth-aachen.de
Author-email: Martin Bellgardt <bellgardt@vr.rwth-aachen.de>
License: MIT License
License-File: LICENSE
Classifier: License :: OSI Approved :: MIT License
Classifier: Operating System :: OS Independent
Classifier: Programming Language :: Python :: 3
Requires-Python: >=3.7
Requires-Dist: anntonia
Requires-Dist: keras
Requires-Dist: numpy
Requires-Dist: scikit-learn
Requires-Dist: scipy
